{
  "__requires": [
    {
      "type": "grafana",
      "id": "grafana",
      "name": "Grafana",
      "version": "6.5.1"
    },
    {
      "type": "panel",
      "id": "graph",
      "name": "Graph",
      "version": ""
    },
    {
      "type": "datasource",
      "id": "prometheus",
      "name": "Prometheus",
      "version": "1.0.0"
    }
  ],
  "annotations": {
    "list": [
      {
        "datasource": "-- Grafana --",
        "enable": true,
        "hide": true,
        "iconColor": "#56A64B",
        "limit": 100,
        "name": "Successful Model Update",
        "showIn": 0,
        "tags": [
          "model-update",
          "fwxserver",
          "success"
        ],
        "type": "tags"
      },
      {
        "datasource": "-- Grafana --",
        "enable": true,
        "hide": true,
        "iconColor": "rgba(255, 96, 96, 1)",
        "limit": 100,
        "name": "Failed Model Update",
        "showIn": 0,
        "tags": [
          "model-update",
          "fwxserver",
          "failed"
        ],
        "type": "tags"
      },
      {
        "datasource": "-- Grafana --",
        "enable": true,
        "hide": true,
        "iconColor": "#3274D9",
        "limit": 100,
        "name": "Model Update started",
        "showIn": 0,
        "tags": [
          "fwxserver",
          "model-update"
        ],
        "type": "tags"
      },
      {
        "builtIn": 1,
        "datasource": "-- Grafana --",
        "enable": true,
        "hide": true,
        "iconColor": "rgba(0, 211, 255, 1)",
        "limit": 100,
        "name": "Annotations & Alerts",
        "showIn": 0,
        "tags": [],
        "type": "dashboard"
      }
    ]
  },
  "description": "Lists application usage by version",
  "editable": true,
  "gnetId": null,
  "graphTooltip": 0,
  "id": null,
  "iteration": 1592137473090,
  "links": [
    {
      "icon": "external link",
      "keepTime": true,
      "tags": [
        "patching"
      ],
      "type": "dashboards"
    }
  ],
  "panels": [
    {
      "collapsed": false,
      "datasource": null,
      "gridPos": {
        "h": 1,
        "w": 24,
        "x": 0,
        "y": 0
      },
      "id": 23,
      "panels": [],
      "title": "Report Links",
      "type": "row"
    },
    {
      "columns": [],
      "datasource": null,
      "description": "Quickly jump to each of the reports in FileWave.",
      "fontSize": "100%",
      "gridPos": {
        "h": 6,
        "w": 12,
        "x": 0,
        "y": 1
      },
      "id": 9,
      "options": {},
      "pageSize": null,
      "showHeader": true,
      "sort": {
        "col": 1,
        "desc": false
      },
      "styles": [
        {
          "alias": "Time",
          "dateFormat": "YYYY-MM-DD HH:mm:ss",
          "pattern": "Time",
          "type": "hidden"
        },
        {
          "alias": "Query Name",
          "colorMode": null,
          "colors": [
            "rgba(245, 54, 54, 0.9)",
            "rgba(237, 129, 40, 0.89)",
            "rgba(50, 172, 45, 0.97)"
          ],
          "dateFormat": "YYYY-MM-DD HH:mm:ss",
          "decimals": 2,
          "link": true,
          "linkTargetBlank": true,
          "linkTooltip": "Jump to report: ${__cell_2}",
          "linkUrl": "https://${server}/reports/${__cell_1}/details",
          "mappingType": 1,
          "pattern": "query_name",
          "thresholds": [],
          "type": "string",
          "unit": "short"
        },
        {
          "alias": "",
          "colorMode": null,
          "colors": [
            "rgba(245, 54, 54, 0.9)",
            "rgba(237, 129, 40, 0.89)",
            "rgba(50, 172, 45, 0.97)"
          ],
          "dateFormat": "YYYY-MM-DD HH:mm:ss",
          "decimals": 2,
          "mappingType": 1,
          "pattern": "Value",
          "thresholds": [],
          "type": "hidden",
          "unit": "short"
        },
        {
          "alias": "",
          "colorMode": null,
          "colors": [
            "rgba(245, 54, 54, 0.9)",
            "rgba(237, 129, 40, 0.89)",
            "rgba(50, 172, 45, 0.97)"
          ],
          "dateFormat": "YYYY-MM-DD HH:mm:ss",
          "decimals": 2,
          "mappingType": 1,
          "pattern": "query_id",
          "thresholds": [],
          "type": "hidden",
          "unit": "short"
        },
        {
          "alias": "",
          "colorMode": null,
          "colors": [
            "rgba(245, 54, 54, 0.9)",
            "rgba(237, 129, 40, 0.89)",
            "rgba(50, 172, 45, 0.97)"
          ],
          "decimals": 2,
          "pattern": "/.*/",
          "thresholds": [],
          "type": "string",
          "unit": "short"
        }
      ],
      "targets": [
        {
          "expr": "count(extra_metrics_application_version) by (query_name, query_id)",
          "format": "table",
          "instant": true,
          "legendFormat": "",
          "refId": "A"
        }
      ],
      "timeFrom": null,
      "timeShift": null,
      "title": "Reports Quick Links",
      "transform": "table",
      "type": "table"
    },
    {
      "collapsed": false,
      "datasource": null,
      "gridPos": {
        "h": 1,
        "w": 24,
        "x": 0,
        "y": 7
      },
      "id": 30,
      "panels": [],
      "repeat": null,
      "title": "Application Version Reports",
      "type": "row"
    },
    {
      "aliasColors": {},
      "bars": true,
      "dashLength": 10,
      "dashes": false,
      "datasource": "FileWave Prometheus",
      "decimals": 0,
      "description": "",
      "fill": 1,
      "fillGradient": 0,
      "gridPos": {
        "h": 8,
        "w": 12,
        "x": 0,
        "y": 8
      },
      "hiddenSeries": false,
      "id": 2,
      "legend": {
        "alignAsTable": true,
        "avg": false,
        "current": true,
        "hideEmpty": false,
        "hideZero": false,
        "max": false,
        "min": false,
        "rightSide": false,
        "show": false,
        "total": false,
        "values": true
      },
      "lines": false,
      "linewidth": 1,
      "links": [],
      "maxPerRow": 2,
      "nullPointMode": "null",
      "options": {
        "dataLinks": []
      },
      "percentage": false,
      "pointradius": 2,
      "points": false,
      "renderer": "flot",
      "repeat": "query_name",
      "repeatDirection": "h",
      "scopedVars": {
        "query_name": {
          "selected": false,
          "text": "Office Mac",
          "value": "Office Mac"
        }
      },
      "seriesOverrides": [],
      "spaceLength": 10,
      "stack": false,
      "steppedLine": false,
      "targets": [
        {
          "datasource": "FileWave Prometheus",
          "expr": "extra_metrics_application_version{query_name=\"${query_name}\"}",
          "format": "time_series",
          "instant": true,
          "legendFormat": "{{application_version}}",
          "refId": "A"
        }
      ],
      "thresholds": [],
      "timeFrom": null,
      "timeRegions": [],
      "timeShift": null,
      "title": "${query_name}",
      "tooltip": {
        "shared": false,
        "sort": 2,
        "value_type": "individual"
      },
      "type": "graph",
      "xaxis": {
        "buckets": null,
        "mode": "series",
        "name": null,
        "show": true,
        "values": [
          "total"
        ]
      },
      "yaxes": [
        {
          "format": "short",
          "label": "Count",
          "logBase": 1,
          "max": null,
          "min": null,
          "show": true
        },
        {
          "format": "short",
          "label": "",
          "logBase": 1,
          "max": null,
          "min": null,
          "show": false
        }
      ],
      "yaxis": {
        "align": false,
        "alignLevel": null
      }
    },
    {
      "aliasColors": {},
      "bars": true,
      "dashLength": 10,
      "dashes": false,
      "datasource": "FileWave Prometheus",
      "decimals": 0,
      "description": "",
      "fill": 1,
      "fillGradient": 0,
      "gridPos": {
        "h": 8,
        "w": 12,
        "x": 12,
        "y": 8
      },
      "hiddenSeries": false,
      "id": 31,
      "legend": {
        "alignAsTable": true,
        "avg": false,
        "current": true,
        "hideEmpty": false,
        "hideZero": false,
        "max": false,
        "min": false,
        "rightSide": false,
        "show": false,
        "total": false,
        "values": true
      },
      "lines": false,
      "linewidth": 1,
      "links": [],
      "maxPerRow": 2,
      "nullPointMode": "null",
      "options": {
        "dataLinks": []
      },
      "percentage": false,
      "pointradius": 2,
      "points": false,
      "renderer": "flot",
      "repeat": null,
      "repeatDirection": "h",
      "repeatIteration": 1592413324683,
      "repeatPanelId": 2,
      "scopedVars": {
        "query_name": {
          "selected": false,
          "text": "Adobe Acrobat Reader Win",
          "value": "Adobe Acrobat Reader Win"
        }
      },
      "seriesOverrides": [],
      "spaceLength": 10,
      "stack": false,
      "steppedLine": false,
      "targets": [
        {
          "datasource": "FileWave Prometheus",
          "expr": "extra_metrics_application_version{query_name=\"${query_name}\"}",
          "format": "time_series",
          "instant": true,
          "legendFormat": "{{application_version}}",
          "refId": "A"
        }
      ],
      "thresholds": [],
      "timeFrom": null,
      "timeRegions": [],
      "timeShift": null,
      "title": "${query_name}",
      "tooltip": {
        "shared": false,
        "sort": 2,
        "value_type": "individual"
      },
      "type": "graph",
      "xaxis": {
        "buckets": null,
        "mode": "series",
        "name": null,
        "show": true,
        "values": [
          "total"
        ]
      },
      "yaxes": [
        {
          "format": "short",
          "label": "Count",
          "logBase": 1,
          "max": null,
          "min": null,
          "show": true
        },
        {
          "format": "short",
          "label": "",
          "logBase": 1,
          "max": null,
          "min": null,
          "show": false
        }
      ],
      "yaxis": {
        "align": false,
        "alignLevel": null
      }
    },
    {
      "aliasColors": {},
      "bars": true,
      "dashLength": 10,
      "dashes": false,
      "datasource": "FileWave Prometheus",
      "decimals": 0,
      "description": "",
      "fill": 1,
      "fillGradient": 0,
      "gridPos": {
        "h": 8,
        "w": 12,
        "x": 0,
        "y": 16
      },
      "hiddenSeries": false,
      "id": 32,
      "legend": {
        "alignAsTable": true,
        "avg": false,
        "current": true,
        "hideEmpty": false,
        "hideZero": false,
        "max": false,
        "min": false,
        "rightSide": false,
        "show": false,
        "total": false,
        "values": true
      },
      "lines": false,
      "linewidth": 1,
      "links": [],
      "maxPerRow": 2,
      "nullPointMode": "null",
      "options": {
        "dataLinks": []
      },
      "percentage": false,
      "pointradius": 2,
      "points": false,
      "renderer": "flot",
      "repeat": null,
      "repeatDirection": "h",
      "repeatIteration": 1592413324683,
      "repeatPanelId": 2,
      "scopedVars": {
        "query_name": {
          "selected": false,
          "text": "VLC Windows",
          "value": "VLC Windows"
        }
      },
      "seriesOverrides": [],
      "spaceLength": 10,
      "stack": false,
      "steppedLine": false,
      "targets": [
        {
          "datasource": "FileWave Prometheus",
          "expr": "extra_metrics_application_version{query_name=\"${query_name}\"}",
          "format": "time_series",
          "instant": true,
          "legendFormat": "{{application_version}}",
          "refId": "A"
        }
      ],
      "thresholds": [],
      "timeFrom": null,
      "timeRegions": [],
      "timeShift": null,
      "title": "${query_name}",
      "tooltip": {
        "shared": false,
        "sort": 2,
        "value_type": "individual"
      },
      "type": "graph",
      "xaxis": {
        "buckets": null,
        "mode": "series",
        "name": null,
        "show": true,
        "values": [
          "total"
        ]
      },
      "yaxes": [
        {
          "format": "short",
          "label": "Count",
          "logBase": 1,
          "max": null,
          "min": null,
          "show": true
        },
        {
          "format": "short",
          "label": "",
          "logBase": 1,
          "max": null,
          "min": null,
          "show": false
        }
      ],
      "yaxis": {
        "align": false,
        "alignLevel": null
      }
    },
    {
      "aliasColors": {},
      "bars": true,
      "dashLength": 10,
      "dashes": false,
      "datasource": "FileWave Prometheus",
      "decimals": 0,
      "description": "",
      "fill": 1,
      "fillGradient": 0,
      "gridPos": {
        "h": 8,
        "w": 12,
        "x": 12,
        "y": 16
      },
      "hiddenSeries": false,
      "id": 33,
      "legend": {
        "alignAsTable": true,
        "avg": false,
        "current": true,
        "hideEmpty": false,
        "hideZero": false,
        "max": false,
        "min": false,
        "rightSide": false,
        "show": false,
        "total": false,
        "values": true
      },
      "lines": false,
      "linewidth": 1,
      "links": [],
      "maxPerRow": 2,
      "nullPointMode": "null",
      "options": {
        "dataLinks": []
      },
      "percentage": false,
      "pointradius": 2,
      "points": false,
      "renderer": "flot",
      "repeat": null,
      "repeatDirection": "h",
      "repeatIteration": 1592413324683,
      "repeatPanelId": 2,
      "scopedVars": {
        "query_name": {
          "selected": false,
          "text": "Zoom Win",
          "value": "Zoom Win"
        }
      },
      "seriesOverrides": [],
      "spaceLength": 10,
      "stack": false,
      "steppedLine": false,
      "targets": [
        {
          "datasource": "FileWave Prometheus",
          "expr": "extra_metrics_application_version{query_name=\"${query_name}\"}",
          "format": "time_series",
          "instant": true,
          "legendFormat": "{{application_version}}",
          "refId": "A"
        }
      ],
      "thresholds": [],
      "timeFrom": null,
      "timeRegions": [],
      "timeShift": null,
      "title": "${query_name}",
      "tooltip": {
        "shared": false,
        "sort": 2,
        "value_type": "individual"
      },
      "type": "graph",
      "xaxis": {
        "buckets": null,
        "mode": "series",
        "name": null,
        "show": true,
        "values": [
          "total"
        ]
      },
      "yaxes": [
        {
          "format": "short",
          "label": "Count",
          "logBase": 1,
          "max": null,
          "min": null,
          "show": true
        },
        {
          "format": "short",
          "label": "",
          "logBase": 1,
          "max": null,
          "min": null,
          "show": false
        }
      ],
      "yaxis": {
        "align": false,
        "alignLevel": null
      }
    },
    {
      "aliasColors": {},
      "bars": true,
      "dashLength": 10,
      "dashes": false,
      "datasource": "FileWave Prometheus",
      "decimals": 0,
      "description": "",
      "fill": 1,
      "fillGradient": 0,
      "gridPos": {
        "h": 8,
        "w": 12,
        "x": 0,
        "y": 24
      },
      "hiddenSeries": false,
      "id": 34,
      "legend": {
        "alignAsTable": true,
        "avg": false,
        "current": true,
        "hideEmpty": false,
        "hideZero": false,
        "max": false,
        "min": false,
        "rightSide": false,
        "show": false,
        "total": false,
        "values": true
      },
      "lines": false,
      "linewidth": 1,
      "links": [],
      "maxPerRow": 2,
      "nullPointMode": "null",
      "options": {
        "dataLinks": []
      },
      "percentage": false,
      "pointradius": 2,
      "points": false,
      "renderer": "flot",
      "repeat": null,
      "repeatDirection": "h",
      "repeatIteration": 1592413324683,
      "repeatPanelId": 2,
      "scopedVars": {
        "query_name": {
          "selected": false,
          "text": "Firefox Windows",
          "value": "Firefox Windows"
        }
      },
      "seriesOverrides": [],
      "spaceLength": 10,
      "stack": false,
      "steppedLine": false,
      "targets": [
        {
          "datasource": "FileWave Prometheus",
          "expr": "extra_metrics_application_version{query_name=\"${query_name}\"}",
          "format": "time_series",
          "instant": true,
          "legendFormat": "{{application_version}}",
          "refId": "A"
        }
      ],
      "thresholds": [],
      "timeFrom": null,
      "timeRegions": [],
      "timeShift": null,
      "title": "${query_name}",
      "tooltip": {
        "shared": false,
        "sort": 2,
        "value_type": "individual"
      },
      "type": "graph",
      "xaxis": {
        "buckets": null,
        "mode": "series",
        "name": null,
        "show": true,
        "values": [
          "total"
        ]
      },
      "yaxes": [
        {
          "format": "short",
          "label": "Count",
          "logBase": 1,
          "max": null,
          "min": null,
          "show": true
        },
        {
          "format": "short",
          "label": "",
          "logBase": 1,
          "max": null,
          "min": null,
          "show": false
        }
      ],
      "yaxis": {
        "align": false,
        "alignLevel": null
      }
    },
    {
      "aliasColors": {},
      "bars": true,
      "dashLength": 10,
      "dashes": false,
      "datasource": "FileWave Prometheus",
      "decimals": 0,
      "description": "",
      "fill": 1,
      "fillGradient": 0,
      "gridPos": {
        "h": 8,
        "w": 12,
        "x": 12,
        "y": 24
      },
      "hiddenSeries": false,
      "id": 35,
      "legend": {
        "alignAsTable": true,
        "avg": false,
        "current": true,
        "hideEmpty": false,
        "hideZero": false,
        "max": false,
        "min": false,
        "rightSide": false,
        "show": false,
        "total": false,
        "values": true
      },
      "lines": false,
      "linewidth": 1,
      "links": [],
      "maxPerRow": 2,
      "nullPointMode": "null",
      "options": {
        "dataLinks": []
      },
      "percentage": false,
      "pointradius": 2,
      "points": false,
      "renderer": "flot",
      "repeat": null,
      "repeatDirection": "h",
      "repeatIteration": 1592413324683,
      "repeatPanelId": 2,
      "scopedVars": {
        "query_name": {
          "selected": false,
          "text": "Google Chrome Win",
          "value": "Google Chrome Win"
        }
      },
      "seriesOverrides": [],
      "spaceLength": 10,
      "stack": false,
      "steppedLine": false,
      "targets": [
        {
          "datasource": "FileWave Prometheus",
          "expr": "extra_metrics_application_version{query_name=\"${query_name}\"}",
          "format": "time_series",
          "instant": true,
          "legendFormat": "{{application_version}}",
          "refId": "A"
        }
      ],
      "thresholds": [],
      "timeFrom": null,
      "timeRegions": [],
      "timeShift": null,
      "title": "${query_name}",
      "tooltip": {
        "shared": false,
        "sort": 2,
        "value_type": "individual"
      },
      "type": "graph",
      "xaxis": {
        "buckets": null,
        "mode": "series",
        "name": null,
        "show": true,
        "values": [
          "total"
        ]
      },
      "yaxes": [
        {
          "format": "short",
          "label": "Count",
          "logBase": 1,
          "max": null,
          "min": null,
          "show": true
        },
        {
          "format": "short",
          "label": "",
          "logBase": 1,
          "max": null,
          "min": null,
          "show": false
        }
      ],
      "yaxis": {
        "align": false,
        "alignLevel": null
      }
    }
  ],
  "refresh": "30s",
  "schemaVersion": 21,
  "style": "dark",
  "tags": [
    "patching"
  ],
  "templating": {
    "list": [
      {
        "allValue": null,
        "current": {
          "text": "All",
          "value": [
            "$__all"
          ]
        },
        "datasource": "FileWave Prometheus",
        "definition": "extra_metrics_application_version",
        "hide": 0,
        "includeAll": true,
        "label": "App Name",
        "multi": true,
        "name": "query_name",
        "options": [],
        "query": "extra_metrics_application_version",
        "refresh": 2,
        "regex": "/.*query_name=\"(.+)\".*/",
        "skipUrlSync": false,
        "sort": 0,
        "tagValuesQuery": "/.*query_name=\"(.*)\",.*/",
        "tags": [],
        "tagsQuery": "extra_metrics_application_version",
        "type": "query",
        "useTags": false
      },
      {
        "current": {
          "value": "${VAR_SERVER}",
          "text": "${VAR_SERVER}"
        },
        "hide": 2,
        "label": "Server",
        "name": "server",
        "options": [
          {
            "selected": true,
            "value": "${VAR_SERVER}",
            "text": "${VAR_SERVER}"
          }
        ],
        "query": "${VAR_SERVER}",
        "skipUrlSync": false,
        "type": "constant"
      }
    ]
  },
  "timepicker": {
    "refresh_intervals": [
      "5s",
      "10s",
      "30s",
      "1m",
      "5m",
      "15m",
      "30m",
      "1h",
      "2h",
      "1d"
    ]
  },
  "timezone": "",
  "title": "Applications"
}